LICENSE
MANIFEST.in
README.md
setup.py
django_swiftbrowser.egg-info/PKG-INFO
django_swiftbrowser.egg-info/SOURCES.txt
django_swiftbrowser.egg-info/dependency_links.txt
django_swiftbrowser.egg-info/not-zip-safe
django_swiftbrowser.egg-info/pbr.json
django_swiftbrowser.egg-info/requires.txt
django_swiftbrowser.egg-info/top_level.txt
swiftbrowser/__init__.py
swiftbrowser/forms.py
swiftbrowser/models.py
swiftbrowser/settings.py
swiftbrowser/urls.py
swiftbrowser/utils.py
swiftbrowser/views.py
swiftbrowser/templates/404.html
swiftbrowser/templates/500.html
swiftbrowser/templates/addacl_modal.html
swiftbrowser/templates/base.html
swiftbrowser/templates/containerview.html
swiftbrowser/templates/core.html
swiftbrowser/templates/create_container.html
swiftbrowser/templates/create_pseudofolder.html
swiftbrowser/templates/edit_acl.html
swiftbrowser/templates/login.html
swiftbrowser/templates/messages.html
swiftbrowser/templates/objectview.html
swiftbrowser/templates/publicview.html
swiftbrowser/templates/tempurl.html
swiftbrowser/templates/upload_form.html
swiftbrowser/templates/upload_modal.html
swiftbrowser/templatetags/__init__.py
swiftbrowser/templatetags/dateconv.py
swiftbrowser/templatetags/lastpart.py