Metadata-Version: 1.1
Name: django-swiftbrowser
Version: 0.21
Summary: A simple Django app to access Openstack Swift
Home-page: https://github.com/cschwede/django-swiftbrowser
Author: Christian Schwede
Author-email: info@cschwede.de
License: Apache License (2.0)
Platform: UNKNOWN
Classifier: Environment :: Web Environment
Classifier: Framework :: Django
Classifier: Intended Audience :: Developers
Classifier: License :: OSI Approved :: Apache Software License
Classifier: Operating System :: OS Independent
Classifier: Programming Language :: Python
Classifier: Programming Language :: Python :: 2.6
Classifier: Programming Language :: Python :: 2.7
Classifier: Topic :: Internet :: WWW/HTTP
Classifier: Topic :: Internet :: WWW/HTTP :: Dynamic Content
